merkleproof/__init__.py
merkleproof/__version__.py
merkleproof/tree.py
merkleproof-0.0.1.dist-info/LICENSE
merkleproof-0.0.1.dist-info/WHEEL
merkleproof-0.0.1.dist-info/METADATA
merkleproof-0.0.1.dist-info/RECORD
