Metadata-Version: 2.1
Name: merkleproof
Version: 0.0.1
Summary: 
Author: Carl Oscar Aaro
Author-email: hello@carloscar.com
Requires-Python: >=3.8,<4.0
Classifier: Programming Language :: Python :: 3
Classifier: Programming Language :: Python :: 3.8
Classifier: Programming Language :: Python :: 3.9
Classifier: Programming Language :: Python :: 3.10
Classifier: Programming Language :: Python :: 3.11
